autowebx/__init__.py
autowebx/account.py
autowebx/auto_save_dict.py
autowebx/auto_save_list.py
autowebx/auto_save_queue.py
autowebx/auto_save_set.py
autowebx/azcaptcha.py
autowebx/capsolver.py
autowebx/communications.py
autowebx/email_fake.py
autowebx/files.py
autowebx/five_sim.py
autowebx/human_wright.py
autowebx/inboxes.py
autowebx/mail_tm.py
autowebx/mediafire.py
autowebx/panels.py
autowebx/proxy.py
autowebx/remotix.py
autowebx/remotix_mail.py
autowebx/temp_mail.py
autowebx/tempm.py
autowebx/twentytwodo.py
autowebx/two_captcha.py
scriptor/__init__.py
scriptor/test.py
scriptor/utils.py
autowebx-1.11.dist-info/METADATA
autowebx-1.11.dist-info/WHEEL
autowebx-1.11.dist-info/entry_points.txt
autowebx-1.11.dist-info/top_level.txt
autowebx-1.11.dist-info/RECORD
