Metadata-Version: 2.4
Name: autowebx
Version: 1.11
Summary: Automation helpers: temp email, captcha solvers, proxies, Playwright humanizer, and more
Requires-Python: >=3.9
Requires-Dist: requests>=2.31.0
Requires-Dist: beautifulsoup4>=4.12.2
Requires-Dist: names>=0.3.0
Requires-Dist: phonenumbers>=8.13.0
Requires-Dist: colorama>=0.4.6
Requires-Dist: art>=6.5
Requires-Dist: multipledispatch>=1.0.0
Requires-Dist: ntplib>=0.4.0
Dynamic: description
Dynamic: description-content-type
Dynamic: requires-dist
Dynamic: requires-python
Dynamic: summary
